{"positionDefinitions":[{"name":"656c95db","positions":[{"x":0.0,"y":0.0,"z":0.0}],"positionsFlipped":[]},{"name":"2998e79","positions":[{"x":0.0,"y":0.0,"z":0.0}],"positionsFlipped":[]},{"name":"d349400d","positions":[{"x":0.0,"y":0.0,"z":0.0}],"positionsFlipped":[]},{"name":"bb344319","positions":[{"x":0.0,"y":0.0,"z":0.0}],"positionsFlipped":[]},{"name":"95ffc93f","positions":[{"x":0.0,"y":0.0,"z":0.0}],"positionsFlipped":[]},{"name":"34a1a672","positions":[{"x":0.0,"y":0.0,"z":0.0}],"positionsFlipped":[]},{"name":"780b83e9","positions":[{"x":0.0,"y":0.0,"z":0.0}],"positionsFlipped":[]},{"name":"d63c51bc","positions":[{"x":0.0,"y":0.0,"z":0.0}],"positionsFlipped":[]},{"name":"51da965","positions":[{"x":0.0,"y":0.0,"z":0.0}],"positionsFlipped":[]}]}