{"positionDefinitions":[{"name":"c161fc3a","positions":[],"positionsFlipped":[{"x":0.0,"y":0.0,"z":0.0}]},{"name":"b4e82873","positions":[],"positionsFlipped":[{"x":0.0,"y":0.0,"z":0.0}]},{"name":"2b6dc3b5","positions":[],"positionsFlipped":[{"x":0.0,"y":0.0,"z":0.0}]},{"name":"17cc5eed","positions":[],"positionsFlipped":[{"x":0.0,"y":0.0,"z":0.0}]},{"name":"c8e7b387","positions":[{"x":0.0,"y":0.0,"z":0.0}],"positionsFlipped":[]},{"name":"40feb7e2","positions":[{"x":0.0,"y":0.0,"z":0.0}],"positionsFlipped":[]},{"name":"b41bfe3c","positions":[{"x":0.0,"y":0.0,"z":0.0}],"positionsFlipped":[]},{"name":"56237ae3","positions":[{"x":0.0,"y":0.0,"z":0.0}],"positionsFlipped":[]},{"name":"ae859bf0","positions":[{"x":0.0,"y":0.0,"z":0.0}],"positionsFlipped":[]},{"name":"15df7f58","positions":[{"x":0.0,"y":0.0,"z":0.0}],"positionsFlipped":[]},{"name":"8d0eaff9","positions":[{"x":0.0,"y":0.0,"z":0.0}],"positionsFlipped":[]},{"name":"8246b04e","positions":[{"x":0.0,"y":0.0,"z":0.0}],"positionsFlipped":[]}]}