{"positionDefinitions":[{"name":"73074bbd","positions":[{"x":0.0,"y":0.0,"z":0.0}],"positionsFlipped":[]},{"name":"37cb8c14","positions":[{"x":0.0,"y":0.0,"z":0.0}],"positionsFlipped":[]},{"name":"c61c439f","positions":[{"x":0.0,"y":0.0,"z":0.0}],"positionsFlipped":[]},{"name":"b1940484","positions":[{"x":0.0,"y":0.0,"z":0.0}],"positionsFlipped":[]},{"name":"a3beb39c","positions":[{"x":0.0,"y":0.0,"z":0.0}],"positionsFlipped":[]},{"name":"c6286877","positions":[{"x":0.0,"y":0.0,"z":0.0}],"positionsFlipped":[]},{"name":"ff3bf3bc","positions":[{"x":0.0,"y":0.0,"z":0.0}],"positionsFlipped":[]},{"name":"5a3d7201","positions":[{"x":0.0,"y":0.0,"z":0.0}],"positionsFlipped":[]},{"name":"73ec6f83","positions":[{"x":0.0,"y":0.0,"z":0.0}],"positionsFlipped":[]},{"name":"c9b11f13","positions":[{"x":0.0,"y":0.0,"z":0.0}],"positionsFlipped":[]},{"name":"ce4402db","positions":[{"x":0.0,"y":0.0,"z":0.0}],"positionsFlipped":[]},{"name":"93393705","positions":[{"x":0.0,"y":0.0,"z":0.0}],"positionsFlipped":[]}]}