{"positionDefinitions":[{"name":"72157cde","positions":[{"x":0.0,"y":0.0,"z":0.0}],"positionsFlipped":[]},{"name":"ec2cf067","positions":[{"x":0.0,"y":0.0,"z":0.0}],"positionsFlipped":[]},{"name":"b5ea1a25","positions":[{"x":0.0,"y":0.0,"z":0.0}],"positionsFlipped":[]},{"name":"c09b65b","positions":[{"x":0.0,"y":0.0,"z":0.0}],"positionsFlipped":[]},{"name":"7942b09a","positions":[{"x":0.0,"y":0.0,"z":0.0}],"positionsFlipped":[]},{"name":"85ee1550","positions":[{"x":0.0,"y":0.0,"z":0.0}],"positionsFlipped":[]},{"name":"e4101449","positions":[{"x":0.0,"y":0.0,"z":0.0}],"positionsFlipped":[]},{"name":"e958c35b","positions":[{"x":0.0,"y":0.0,"z":0.0}],"positionsFlipped":[]},{"name":"7ed8de8e","positions":[{"x":0.0,"y":0.0,"z":0.0}],"positionsFlipped":[]},{"name":"693032da","positions":[{"x":0.0,"y":0.0,"z":0.0}],"positionsFlipped":[]},{"name":"2e5ec54c","positions":[{"x":0.0,"y":0.0,"z":0.0}],"positionsFlipped":[]},{"name":"f2b3b7bc","positions":[{"x":0.0,"y":0.0,"z":0.0}],"positionsFlipped":[]},{"name":"12c72f74","positions":[{"x":0.0,"y":0.0,"z":0.0}],"positionsFlipped":[]},{"name":"e8f82f91","positions":[{"x":0.0,"y":0.0,"z":0.0}],"positionsFlipped":[]}]}