{"parts":[{"names":["1980_Innenwand"],"positionDefinitions":["8b999e95"],"condition":"NORMAL","renderStage":"INTERIOR","type":"NORMAL","displayXPadding":0.0,"displayYPadding":0.0,"displayColorCjk":"","displayColor":"","displayMaxLineHeight":0.0,"displayCjkSizeRatio":0.0,"displayOptions":[],"displayPadZeros":0.0,"displayType":"DESTINATION","displayDefaultText":"","doorXMultiplier":0.0,"doorZMultiplier":0.0,"doorAnimationType":"PLUG_FAST","renderFromOpeningDoorTime":0,"renderUntilOpeningDoorTime":0,"renderFromClosingDoorTime":0,"renderUntilClosingDoorTime":0,"flashOffTime":0,"flashOnTime":0},{"names":["1980_Fahrerkabine"],"positionDefinitions":["c2210c25"],"condition":"NORMAL","renderStage":"EXTERIOR","type":"NORMAL","displayXPadding":0.0,"displayYPadding":0.0,"displayColorCjk":"","displayColor":"","displayMaxLineHeight":0.0,"displayCjkSizeRatio":0.0,"displayOptions":[],"displayPadZeros":0.0,"displayType":"DESTINATION","displayDefaultText":"","doorXMultiplier":0.0,"doorZMultiplier":0.0,"doorAnimationType":"PLUG_FAST","renderFromOpeningDoorTime":0,"renderUntilOpeningDoorTime":0,"renderFromClosingDoorTime":0,"renderUntilClosingDoorTime":0,"flashOffTime":0,"flashOnTime":0},{"names":["1980_Aussenwand"],"positionDefinitions":["36ec83c5"],"condition":"NORMAL","renderStage":"EXTERIOR","type":"NORMAL","displayXPadding":0.0,"displayYPadding":0.0,"displayColorCjk":"","displayColor":"","displayMaxLineHeight":0.0,"displayCjkSizeRatio":0.0,"displayOptions":[],"displayPadZeros":0.0,"displayType":"DESTINATION","displayDefaultText":"","doorXMultiplier":0.0,"doorZMultiplier":0.0,"doorAnimationType":"PLUG_FAST","renderFromOpeningDoorTime":0,"renderUntilOpeningDoorTime":0,"renderFromClosingDoorTime":0,"renderUntilClosingDoorTime":0,"flashOffTime":0,"flashOnTime":0},{"names":["1980_Tuer_A"],"positionDefinitions":["a56f2d9e"],"condition":"NORMAL","renderStage":"EXTERIOR","type":"NORMAL","displayXPadding":0.0,"displayYPadding":0.0,"displayColorCjk":"","displayColor":"","displayMaxLineHeight":0.0,"displayCjkSizeRatio":0.0,"displayOptions":[],"displayPadZeros":0.0,"displayType":"DESTINATION","displayDefaultText":"","doorXMultiplier":-1.0,"doorZMultiplier":12.0,"doorAnimationType":"PLUG_FAST","renderFromOpeningDoorTime":0,"renderUntilOpeningDoorTime":0,"renderFromClosingDoorTime":0,"renderUntilClosingDoorTime":0,"flashOffTime":0,"flashOnTime":0},{"names":["1980_Tuer_B"],"positionDefinitions":["41fa94ca"],"condition":"NORMAL","renderStage":"EXTERIOR","type":"NORMAL","displayXPadding":0.0,"displayYPadding":0.0,"displayColorCjk":"","displayColor":"","displayMaxLineHeight":0.0,"displayCjkSizeRatio":0.0,"displayOptions":[],"displayPadZeros":0.0,"displayType":"DESTINATION","displayDefaultText":"","doorXMultiplier":-1.0,"doorZMultiplier":-12.0,"doorAnimationType":"PLUG_FAST","renderFromOpeningDoorTime":0,"renderUntilOpeningDoorTime":0,"renderFromClosingDoorTime":0,"renderUntilClosingDoorTime":0,"flashOffTime":0,"flashOnTime":0},{"names":["1980_Tuer_A"],"positionDefinitions":["72ad9b5b"],"condition":"NORMAL","renderStage":"EXTERIOR","type":"NORMAL","displayXPadding":0.0,"displayYPadding":0.0,"displayColorCjk":"","displayColor":"","displayMaxLineHeight":0.0,"displayCjkSizeRatio":0.0,"displayOptions":[],"displayPadZeros":0.0,"displayType":"DESTINATION","displayDefaultText":"","doorXMultiplier":-1.0,"doorZMultiplier":12.0,"doorAnimationType":"PLUG_FAST","renderFromOpeningDoorTime":0,"renderUntilOpeningDoorTime":0,"renderFromClosingDoorTime":0,"renderUntilClosingDoorTime":0,"flashOffTime":0,"flashOnTime":0},{"names":["1980_Tuer_B"],"positionDefinitions":["dcfebb29"],"condition":"NORMAL","renderStage":"EXTERIOR","type":"NORMAL","displayXPadding":0.0,"displayYPadding":0.0,"displayColorCjk":"","displayColor":"","displayMaxLineHeight":0.0,"displayCjkSizeRatio":0.0,"displayOptions":[],"displayPadZeros":0.0,"displayType":"DESTINATION","displayDefaultText":"","doorXMultiplier":-1.0,"doorZMultiplier":-12.0,"doorAnimationType":"PLUG_FAST","renderFromOpeningDoorTime":0,"renderUntilOpeningDoorTime":0,"renderFromClosingDoorTime":0,"renderUntilClosingDoorTime":0,"flashOffTime":0,"flashOnTime":0},{"names":["1980_LinienanzeigeAussen"],"positionDefinitions":["5ee58c23"],"condition":"NORMAL","renderStage":"EXTERIOR","type":"DISPLAY","displayXPadding":0.0,"displayYPadding":0.0,"displayColorCjk":"ff9900","displayColor":"ff9900","displayMaxLineHeight":0.0,"displayCjkSizeRatio":0.0,"displayOptions":[],"displayPadZeros":0.0,"displayType":"ROUTE_NUMBER","displayDefaultText":"","doorXMultiplier":0.0,"doorZMultiplier":0.0,"doorAnimationType":"PLUG_FAST","renderFromOpeningDoorTime":0,"renderUntilOpeningDoorTime":0,"renderFromClosingDoorTime":0,"renderUntilClosingDoorTime":0,"flashOffTime":0,"flashOnTime":0},{"names":["1980_ZielanzeigeAussen"],"positionDefinitions":["c7204d7b"],"condition":"NORMAL","renderStage":"EXTERIOR","type":"DISPLAY","displayXPadding":0.0,"displayYPadding":0.0,"displayColorCjk":"ff9900","displayColor":"ff9900","displayMaxLineHeight":0.0,"displayCjkSizeRatio":0.0,"displayOptions":[],"displayPadZeros":0.0,"displayType":"DESTINATION","displayDefaultText":"","doorXMultiplier":0.0,"doorZMultiplier":0.0,"doorAnimationType":"PLUG_FAST","renderFromOpeningDoorTime":0,"renderUntilOpeningDoorTime":0,"renderFromClosingDoorTime":0,"renderUntilClosingDoorTime":0,"flashOffTime":0,"flashOnTime":0},{"names":["1980_Tuer_A_Innen"],"positionDefinitions":["d548872d"],"condition":"NORMAL","renderStage":"INTERIOR","type":"NORMAL","displayXPadding":0.0,"displayYPadding":0.0,"displayColorCjk":"","displayColor":"","displayMaxLineHeight":0.0,"displayCjkSizeRatio":0.0,"displayOptions":[],"displayPadZeros":0.0,"displayType":"DESTINATION","displayDefaultText":"","doorXMultiplier":-1.0,"doorZMultiplier":12.0,"doorAnimationType":"PLUG_FAST","renderFromOpeningDoorTime":0,"renderUntilOpeningDoorTime":0,"renderFromClosingDoorTime":0,"renderUntilClosingDoorTime":0,"flashOffTime":0,"flashOnTime":0},{"names":["1980_Tuer_B_Innen"],"positionDefinitions":["711546bd"],"condition":"NORMAL","renderStage":"INTERIOR","type":"NORMAL","displayXPadding":0.0,"displayYPadding":0.0,"displayColorCjk":"","displayColor":"","displayMaxLineHeight":0.0,"displayCjkSizeRatio":0.0,"displayOptions":[],"displayPadZeros":0.0,"displayType":"DESTINATION","displayDefaultText":"","doorXMultiplier":-1.0,"doorZMultiplier":-12.0,"doorAnimationType":"PLUG_FAST","renderFromOpeningDoorTime":0,"renderUntilOpeningDoorTime":0,"renderFromClosingDoorTime":0,"renderUntilClosingDoorTime":0,"flashOffTime":0,"flashOnTime":0},{"names":["1980_Tuer_A_Innen"],"positionDefinitions":["c6bab5a4"],"condition":"NORMAL","renderStage":"INTERIOR","type":"NORMAL","displayXPadding":0.0,"displayYPadding":0.0,"displayColorCjk":"","displayColor":"","displayMaxLineHeight":0.0,"displayCjkSizeRatio":0.0,"displayOptions":[],"displayPadZeros":0.0,"displayType":"DESTINATION","displayDefaultText":"","doorXMultiplier":-1.0,"doorZMultiplier":12.0,"doorAnimationType":"PLUG_FAST","renderFromOpeningDoorTime":0,"renderUntilOpeningDoorTime":0,"renderFromClosingDoorTime":0,"renderUntilClosingDoorTime":0,"flashOffTime":0,"flashOnTime":0},{"names":["1980_Tuer_B_Innen"],"positionDefinitions":["79db4c47"],"condition":"NORMAL","renderStage":"INTERIOR","type":"NORMAL","displayXPadding":0.0,"displayYPadding":0.0,"displayColorCjk":"","displayColor":"","displayMaxLineHeight":0.0,"displayCjkSizeRatio":0.0,"displayOptions":[],"displayPadZeros":0.0,"displayType":"DESTINATION","displayDefaultText":"","doorXMultiplier":-1.0,"doorZMultiplier":-12.0,"doorAnimationType":"PLUG_FAST","renderFromOpeningDoorTime":0,"renderUntilOpeningDoorTime":0,"renderFromClosingDoorTime":0,"renderUntilClosingDoorTime":0,"flashOffTime":0,"flashOnTime":0},{"names":["1980_Doppelsitz"],"positionDefinitions":["72e9e2d9"],"condition":"NORMAL","renderStage":"INTERIOR","type":"NORMAL","displayXPadding":0.0,"displayYPadding":0.0,"displayColorCjk":"","displayColor":"","displayMaxLineHeight":0.0,"displayCjkSizeRatio":0.0,"displayOptions":[],"displayPadZeros":0.0,"displayType":"DESTINATION","displayDefaultText":"","doorXMultiplier":0.0,"doorZMultiplier":0.0,"doorAnimationType":"PLUG_FAST","renderFromOpeningDoorTime":0,"renderUntilOpeningDoorTime":0,"renderFromClosingDoorTime":0,"renderUntilClosingDoorTime":0,"flashOffTime":0,"flashOnTime":0},{"names":["1980_Doppelsitz"],"positionDefinitions":["ba75163a"],"condition":"NORMAL","renderStage":"INTERIOR","type":"NORMAL","displayXPadding":0.0,"displayYPadding":0.0,"displayColorCjk":"","displayColor":"","displayMaxLineHeight":0.0,"displayCjkSizeRatio":0.0,"displayOptions":[],"displayPadZeros":0.0,"displayType":"DESTINATION","displayDefaultText":"","doorXMultiplier":0.0,"doorZMultiplier":0.0,"doorAnimationType":"PLUG_FAST","renderFromOpeningDoorTime":0,"renderUntilOpeningDoorTime":0,"renderFromClosingDoorTime":0,"renderUntilClosingDoorTime":0,"flashOffTime":0,"flashOnTime":0},{"names":["1980_Einzelsitz"],"positionDefinitions":["d8bcad52"],"condition":"NORMAL","renderStage":"INTERIOR","type":"NORMAL","displayXPadding":0.0,"displayYPadding":0.0,"displayColorCjk":"","displayColor":"","displayMaxLineHeight":0.0,"displayCjkSizeRatio":0.0,"displayOptions":[],"displayPadZeros":0.0,"displayType":"DESTINATION","displayDefaultText":"","doorXMultiplier":0.0,"doorZMultiplier":0.0,"doorAnimationType":"PLUG_FAST","renderFromOpeningDoorTime":0,"renderUntilOpeningDoorTime":0,"renderFromClosingDoorTime":0,"renderUntilClosingDoorTime":0,"flashOffTime":0,"flashOnTime":0},{"names":["1980_Einzelsitz"],"positionDefinitions":["5ce46e2a"],"condition":"NORMAL","renderStage":"INTERIOR","type":"NORMAL","displayXPadding":0.0,"displayYPadding":0.0,"displayColorCjk":"","displayColor":"","displayMaxLineHeight":0.0,"displayCjkSizeRatio":0.0,"displayOptions":[],"displayPadZeros":0.0,"displayType":"DESTINATION","displayDefaultText":"","doorXMultiplier":0.0,"doorZMultiplier":0.0,"doorAnimationType":"PLUG_FAST","renderFromOpeningDoorTime":0,"renderUntilOpeningDoorTime":0,"renderFromClosingDoorTime":0,"renderUntilClosingDoorTime":0,"flashOffTime":0,"flashOnTime":0},{"names":["1980_Sitzpodest_Doppel_A"],"positionDefinitions":["af516c8f"],"condition":"NORMAL","renderStage":"INTERIOR","type":"NORMAL","displayXPadding":0.0,"displayYPadding":0.0,"displayColorCjk":"","displayColor":"","displayMaxLineHeight":0.0,"displayCjkSizeRatio":0.0,"displayOptions":[],"displayPadZeros":0.0,"displayType":"DESTINATION","displayDefaultText":"","doorXMultiplier":0.0,"doorZMultiplier":0.0,"doorAnimationType":"PLUG_FAST","renderFromOpeningDoorTime":0,"renderUntilOpeningDoorTime":0,"renderFromClosingDoorTime":0,"renderUntilClosingDoorTime":0,"flashOffTime":0,"flashOnTime":0},{"names":["1980_Sitzpodest_Doppel_A"],"positionDefinitions":["3b867529"],"condition":"NORMAL","renderStage":"INTERIOR","type":"NORMAL","displayXPadding":0.0,"displayYPadding":0.0,"displayColorCjk":"","displayColor":"","displayMaxLineHeight":0.0,"displayCjkSizeRatio":0.0,"displayOptions":[],"displayPadZeros":0.0,"displayType":"DESTINATION","displayDefaultText":"","doorXMultiplier":0.0,"doorZMultiplier":0.0,"doorAnimationType":"PLUG_FAST","renderFromOpeningDoorTime":0,"renderUntilOpeningDoorTime":0,"renderFromClosingDoorTime":0,"renderUntilClosingDoorTime":0,"flashOffTime":0,"flashOnTime":0},{"names":["1980_Sitzpodest_Einzel_A"],"positionDefinitions":["4a450b37"],"condition":"NORMAL","renderStage":"INTERIOR","type":"NORMAL","displayXPadding":0.0,"displayYPadding":0.0,"displayColorCjk":"","displayColor":"","displayMaxLineHeight":0.0,"displayCjkSizeRatio":0.0,"displayOptions":[],"displayPadZeros":0.0,"displayType":"DESTINATION","displayDefaultText":"","doorXMultiplier":0.0,"doorZMultiplier":0.0,"doorAnimationType":"PLUG_FAST","renderFromOpeningDoorTime":0,"renderUntilOpeningDoorTime":0,"renderFromClosingDoorTime":0,"renderUntilClosingDoorTime":0,"flashOffTime":0,"flashOnTime":0},{"names":["1980_Sitzpodest_Einzel_A"],"positionDefinitions":["96d27954"],"condition":"NORMAL","renderStage":"INTERIOR","type":"NORMAL","displayXPadding":0.0,"displayYPadding":0.0,"displayColorCjk":"","displayColor":"","displayMaxLineHeight":0.0,"displayCjkSizeRatio":0.0,"displayOptions":[],"displayPadZeros":0.0,"displayType":"DESTINATION","displayDefaultText":"","doorXMultiplier":0.0,"doorZMultiplier":0.0,"doorAnimationType":"PLUG_FAST","renderFromOpeningDoorTime":0,"renderUntilOpeningDoorTime":0,"renderFromClosingDoorTime":0,"renderUntilClosingDoorTime":0,"flashOffTime":0,"flashOnTime":0},{"names":["1980_LinienAnzInnen"],"positionDefinitions":["3fe4653a"],"condition":"NORMAL","renderStage":"INTERIOR","type":"DISPLAY","displayXPadding":0.0,"displayYPadding":0.0,"displayColorCjk":"f1efef","displayColor":"f1efef","displayMaxLineHeight":0.0,"displayCjkSizeRatio":0.0,"displayOptions":[],"displayPadZeros":0.0,"displayType":"ROUTE_NUMBER","displayDefaultText":"","doorXMultiplier":0.0,"doorZMultiplier":0.0,"doorAnimationType":"PLUG_FAST","renderFromOpeningDoorTime":0,"renderUntilOpeningDoorTime":0,"renderFromClosingDoorTime":0,"renderUntilClosingDoorTime":0,"flashOffTime":0,"flashOnTime":0},{"names":["1980_ZielAnzInnen"],"positionDefinitions":["feb996ba"],"condition":"NORMAL","renderStage":"INTERIOR","type":"DISPLAY","displayXPadding":0.0,"displayYPadding":0.0,"displayColorCjk":"f1efef","displayColor":"f1efef","displayMaxLineHeight":0.0,"displayCjkSizeRatio":0.0,"displayOptions":["SINGLE_LINE"],"displayPadZeros":0.0,"displayType":"DESTINATION","displayDefaultText":"","doorXMultiplier":0.0,"doorZMultiplier":0.0,"doorAnimationType":"PLUG_FAST","renderFromOpeningDoorTime":0,"renderUntilOpeningDoorTime":0,"renderFromClosingDoorTime":0,"renderUntilClosingDoorTime":0,"flashOffTime":0,"flashOnTime":0},{"names":["1980_HaltAnzInnen"],"positionDefinitions":["d1f61daf"],"condition":"NORMAL","renderStage":"INTERIOR","type":"DISPLAY","displayXPadding":0.0,"displayYPadding":0.0,"displayColorCjk":"a10000","displayColor":"a10000","displayMaxLineHeight":0.0,"displayCjkSizeRatio":0.0,"displayOptions":["SINGLE_LINE"],"displayPadZeros":0.0,"displayType":"NEXT_STATION","displayDefaultText":"","doorXMultiplier":0.0,"doorZMultiplier":0.0,"doorAnimationType":"PLUG_FAST","renderFromOpeningDoorTime":0,"renderUntilOpeningDoorTime":0,"renderFromClosingDoorTime":0,"renderUntilClosingDoorTime":0,"flashOffTime":0,"flashOnTime":0},{"names":["1980_TuerwandLang"],"positionDefinitions":["88bda49f"],"condition":"NORMAL","renderStage":"INTERIOR","type":"NORMAL","displayXPadding":0.0,"displayYPadding":0.0,"displayColorCjk":"","displayColor":"","displayMaxLineHeight":0.0,"displayCjkSizeRatio":0.0,"displayOptions":[],"displayPadZeros":0.0,"displayType":"DESTINATION","displayDefaultText":"","doorXMultiplier":0.0,"doorZMultiplier":0.0,"doorAnimationType":"PLUG_FAST","renderFromOpeningDoorTime":0,"renderUntilOpeningDoorTime":0,"renderFromClosingDoorTime":0,"renderUntilClosingDoorTime":0,"flashOffTime":0,"flashOnTime":0},{"names":["1980_TuerwandLang"],"positionDefinitions":["29a127d"],"condition":"NORMAL","renderStage":"INTERIOR","type":"NORMAL","displayXPadding":0.0,"displayYPadding":0.0,"displayColorCjk":"","displayColor":"","displayMaxLineHeight":0.0,"displayCjkSizeRatio":0.0,"displayOptions":[],"displayPadZeros":0.0,"displayType":"DESTINATION","displayDefaultText":"","doorXMultiplier":0.0,"doorZMultiplier":0.0,"doorAnimationType":"PLUG_FAST","renderFromOpeningDoorTime":0,"renderUntilOpeningDoorTime":0,"renderFromClosingDoorTime":0,"renderUntilClosingDoorTime":0,"flashOffTime":0,"flashOnTime":0},{"names":["1980_TuerwandKurz"],"positionDefinitions":["88c11ba"],"condition":"NORMAL","renderStage":"INTERIOR","type":"NORMAL","displayXPadding":0.0,"displayYPadding":0.0,"displayColorCjk":"","displayColor":"","displayMaxLineHeight":0.0,"displayCjkSizeRatio":0.0,"displayOptions":[],"displayPadZeros":0.0,"displayType":"DESTINATION","displayDefaultText":"","doorXMultiplier":0.0,"doorZMultiplier":0.0,"doorAnimationType":"PLUG_FAST","renderFromOpeningDoorTime":0,"renderUntilOpeningDoorTime":0,"renderFromClosingDoorTime":0,"renderUntilClosingDoorTime":0,"flashOffTime":0,"flashOnTime":0},{"names":["1980_TuerwandKurz"],"positionDefinitions":["f521d4bc"],"condition":"NORMAL","renderStage":"INTERIOR","type":"NORMAL","displayXPadding":0.0,"displayYPadding":0.0,"displayColorCjk":"","displayColor":"","displayMaxLineHeight":0.0,"displayCjkSizeRatio":0.0,"displayOptions":[],"displayPadZeros":0.0,"displayType":"DESTINATION","displayDefaultText":"","doorXMultiplier":0.0,"doorZMultiplier":0.0,"doorAnimationType":"PLUG_FAST","renderFromOpeningDoorTime":0,"renderUntilOpeningDoorTime":0,"renderFromClosingDoorTime":0,"renderUntilClosingDoorTime":0,"flashOffTime":0,"flashOnTime":0},{"names":["1980_Innenbeleuchtung"],"positionDefinitions":["9b7808e4"],"condition":"NORMAL","renderStage":"LIGHT","type":"NORMAL","displayXPadding":0.0,"displayYPadding":0.0,"displayColorCjk":"","displayColor":"","displayMaxLineHeight":0.0,"displayCjkSizeRatio":0.0,"displayOptions":[],"displayPadZeros":0.0,"displayType":"DESTINATION","displayDefaultText":"","doorXMultiplier":0.0,"doorZMultiplier":0.0,"doorAnimationType":"PLUG_FAST","renderFromOpeningDoorTime":0,"renderUntilOpeningDoorTime":0,"renderFromClosingDoorTime":0,"renderUntilClosingDoorTime":0,"flashOffTime":0,"flashOnTime":0},{"names":["1980_Fuehrerstandinterior"],"positionDefinitions":["e8182c41"],"condition":"NORMAL","renderStage":"EXTERIOR","type":"NORMAL","displayXPadding":0.0,"displayYPadding":0.0,"displayColorCjk":"","displayColor":"","displayMaxLineHeight":0.0,"displayCjkSizeRatio":0.0,"displayOptions":[],"displayPadZeros":0.0,"displayType":"DESTINATION","displayDefaultText":"","doorXMultiplier":0.0,"doorZMultiplier":0.0,"doorAnimationType":"PLUG_FAST","renderFromOpeningDoorTime":0,"renderUntilOpeningDoorTime":0,"renderFromClosingDoorTime":0,"renderUntilClosingDoorTime":0,"flashOffTime":0,"flashOnTime":0}],"modelYOffset":1.0,"gangwayInnerSideResource":"mtr:s43tec_lrt2010/testtram_connector_side.png","gangwayInnerTopResource":"mtr:s43tec_lrt2010/testtram_connector_roof.png","gangwayInnerBottomResource":"mtr:s43tec_lrt2010/testtram_connector_floor.png","gangwayOuterSideResource":"mtr:s43tec_lrt2010/testtram_connector_exterior.png","gangwayOuterTopResource":"mtr:s43tec_lrt2010/testtram_connector_exterior.png","gangwayOuterBottomResource":"mtr:s43tec_lrt2010/testtram_connector_exterior.png","gangwayWidth":1.5,"gangwayHeight":2.25,"gangwayYOffset":1.0,"gangwayZOffset":0.5,"barrierInnerSideResource":"_exterior.png","barrierInnerTopResource":"","barrierInnerBottomResource":"","barrierOuterSideResource":"_exterior.png","barrierOuterTopResource":"","barrierOuterBottomResource":"","barrierWidth":2.25,"barrierHeight":1.0,"barrierYOffset":1.25,"barrierZOffset":0.25}